["{\"isPanel\":false,\"surveyCountry\":\"United States\",\"surveyQuestion\":\"Would you be willing to spend $3,500 for an augmented-reality headset from Apple?\",\"surveyAnswers\":[\"Yes\",\"No\"],\"customQuestionsAndResponses\":[{\"question\":\"Do you use Apple products (e.g. iPhone, Macbook, iPad)?\",\"response\":\"\",\"options\":[\"Yes\",\"No\"],\"chosenOptionIndex\":0,\"questionType\":\"Multiple choice\"}],\"surveyDescriptions\":[],\"surveyData\":[{\"No\":0.74,\"Yes\":0.26}],\"surveyModel\":\"GSS-v1.0\"}"]